tides/__init__.py
tides/exceptions.py
tides/provider.py
tides-0.1.0.dist-info/LICENSE
tides-0.1.0.dist-info/METADATA
tides-0.1.0.dist-info/WHEEL
tides-0.1.0.dist-info/top_level.txt
tides-0.1.0.dist-info/RECORD
