Metadata-Version: 2.1
Name: tides
Version: 0.1.0
Summary: A wrapper for the tides API
Home-page: https://github.com/ngfgrant/tides
Author: Niall Grant
Author-email: ngfgrant@gmail.com
License: Apache2
Keywords: tides,api-wrapper
Platform: UNKNOWN
Classifier: Development Status :: 3 - Alpha
Classifier: Environment :: Console
Classifier: Intended Audience :: Developers
Classifier: Natural Language :: English
Classifier: License :: OSI Approved :: Apache Software License
Classifier: Programming Language :: Python
Classifier: Programming Language :: Python :: 3
Classifier: Programming Language :: Python :: 3.4
Classifier: Programming Language :: Python :: 3.5
Classifier: Programming Language :: Python :: 3.6
Classifier: Programming Language :: Python :: 3.7
Classifier: Topic :: Software Development :: Libraries :: Python Modules
Requires-Python: >=3
